 
{
  "name": "DMath",
  "version": "0.1",
  "author": [
    "Russell Greene",
    "Riccardo Iaconelli"
  ],
  "url": "TODO",
  "descriptionmsg": "This setups a hook for the <code><nowiki><dmath></nowiki></code> tag, which is the same as <code><nowiki><math></nowiki></code> except it uses block formatting and it is centered.",
  "license-name": "GPL-2.0+",
  "type": "parserhook",
  "AutoloadClasses" : {
    "DMathParse" : "DMathHooks.php"
  },
  "config" : {
    
  },
  "Hooks": {
    "ParserFirstCallInit" : [
      "DMathParse::onParserFirstCallSetup"
    ]
  },
  "manifest_version": 1
  
  
}